<annotation>
	<folder>Highest</folder>
	<filename>U.58ad5c5f-b33f-11ec-bafd-001a7dda7113.jpg</filename>
	<path>C:\Users\Brogan\Desktop\Uni_AP2\code_ap2\Tensorflow\workspace\images\collectedimages\U\Highest\U.58ad5c5f-b33f-11ec-bafd-001a7dda7113.jpg</path>
	<source>
		<database>Unknown</database>
	</source>
	<size>
		<width>640</width>
		<height>480</height>
		<depth>3</depth>
	</size>
	<segmented>0</segmented>
	<object>
		<name>U</name>
		<pose>Unspecified</pose>
		<truncated>0</truncated>
		<difficult>0</difficult>
		<bndbox>
			<xmin>98</xmin>
			<ymin>101</ymin>
			<xmax>141</xmax>
			<ymax>167</ymax>
		</bndbox>
	</object>
	<object>
		<name>T</name>
		<pose>Unspecified</pose>
		<truncated>0</truncated>
		<difficult>0</difficult>
		<bndbox>
			<xmin>224</xmin>
			<ymin>96</ymin>
			<xmax>265</xmax>
			<ymax>160</ymax>
		</bndbox>
	</object>
	<object>
		<name>S</name>
		<pose>Unspecified</pose>
		<truncated>0</truncated>
		<difficult>0</difficult>
		<bndbox>
			<xmin>348</xmin>
			<ymin>91</ymin>
			<xmax>388</xmax>
			<ymax>157</ymax>
		</bndbox>
	</object>
	<object>
		<name>S</name>
		<pose>Unspecified</pose>
		<truncated>0</truncated>
		<difficult>0</difficult>
		<bndbox>
			<xmin>352</xmin>
			<ymin>188</ymin>
			<xmax>392</xmax>
			<ymax>254</ymax>
		</bndbox>
	</object>
	<object>
		<name>S</name>
		<pose>Unspecified</pose>
		<truncated>0</truncated>
		<difficult>0</difficult>
		<bndbox>
			<xmin>356</xmin>
			<ymin>288</ymin>
			<xmax>394</xmax>
			<ymax>355</ymax>
		</bndbox>
	</object>
	<object>
		<name>S</name>
		<pose>Unspecified</pose>
		<truncated>0</truncated>
		<difficult>0</difficult>
		<bndbox>
			<xmin>360</xmin>
			<ymin>388</ymin>
			<xmax>398</xmax>
			<ymax>455</ymax>
		</bndbox>
	</object>
	<object>
		<name>T</name>
		<pose>Unspecified</pose>
		<truncated>0</truncated>
		<difficult>0</difficult>
		<bndbox>
			<xmin>229</xmin>
			<ymin>195</ymin>
			<xmax>269</xmax>
			<ymax>263</ymax>
		</bndbox>
	</object>
	<object>
		<name>T</name>
		<pose>Unspecified</pose>
		<truncated>0</truncated>
		<difficult>0</difficult>
		<bndbox>
			<xmin>232</xmin>
			<ymin>294</ymin>
			<xmax>273</xmax>
			<ymax>362</ymax>
		</bndbox>
	</object>
	<object>
		<name>T</name>
		<pose>Unspecified</pose>
		<truncated>0</truncated>
		<difficult>0</difficult>
		<bndbox>
			<xmin>235</xmin>
			<ymin>395</ymin>
			<xmax>276</xmax>
			<ymax>463</ymax>
		</bndbox>
	</object>
	<object>
		<name>U</name>
		<pose>Unspecified</pose>
		<truncated>0</truncated>
		<difficult>0</difficult>
		<bndbox>
			<xmin>103</xmin>
			<ymin>201</ymin>
			<xmax>146</xmax>
			<ymax>267</ymax>
		</bndbox>
	</object>
	<object>
		<name>U</name>
		<pose>Unspecified</pose>
		<truncated>0</truncated>
		<difficult>0</difficult>
		<bndbox>
			<xmin>104</xmin>
			<ymin>302</ymin>
			<xmax>148</xmax>
			<ymax>368</ymax>
		</bndbox>
	</object>
	<object>
		<name>U</name>
		<pose>Unspecified</pose>
		<truncated>0</truncated>
		<difficult>0</difficult>
		<bndbox>
			<xmin>108</xmin>
			<ymin>403</ymin>
			<xmax>152</xmax>
			<ymax>469</ymax>
		</bndbox>
	</object>
</annotation>
